autoreduce_qp/__init__.py
autoreduce_qp/manage.py
autoreduce_qp/autoreduce_django/__init__.py
autoreduce_qp/autoreduce_django/asgi.py
autoreduce_qp/autoreduce_django/settings.py
autoreduce_qp/autoreduce_django/urls.py
autoreduce_qp/autoreduce_django/wsgi.py
autoreduce_qp/model/__init__.py
autoreduce_qp/model/database/__init__.py
autoreduce_qp/model/database/access.py
autoreduce_qp/model/database/records.py
autoreduce_qp/model/database/tests/__init__.py
autoreduce_qp/model/database/tests/test_access.py
autoreduce_qp/model/database/tests/test_records.py
autoreduce_qp/queue_processor/__init__.py
autoreduce_qp/queue_processor/handle_message.py
autoreduce_qp/queue_processor/instrument_variable_utils.py
autoreduce_qp/queue_processor/queue_listener.py
autoreduce_qp/queue_processor/settings.py
autoreduce_qp/queue_processor/variable_utils.py
autoreduce_qp/queue_processor/reduction/__init__.py
autoreduce_qp/queue_processor/reduction/exceptions.py
autoreduce_qp/queue_processor/reduction/process_manager.py
autoreduce_qp/queue_processor/reduction/runner.py
autoreduce_qp/queue_processor/reduction/service.py
autoreduce_qp/queue_processor/reduction/timeout.py
autoreduce_qp/queue_processor/reduction/utilities.py
autoreduce_qp/queue_processor/reduction/tests/__init__.py
autoreduce_qp/queue_processor/reduction/tests/common.py
autoreduce_qp/queue_processor/reduction/tests/module_to_import.py
autoreduce_qp/queue_processor/reduction/tests/test_process_manager.py
autoreduce_qp/queue_processor/reduction/tests/test_runner.py
autoreduce_qp/queue_processor/reduction/tests/test_service.py
autoreduce_qp/queue_processor/reduction/tests/test_utilities.py
autoreduce_qp/queue_processor/tests/__init__.py
autoreduce_qp/queue_processor/tests/test_handle_message.py
autoreduce_qp/queue_processor/tests/test_instrument_variable_utils.py
autoreduce_qp/queue_processor/tests/test_queue_listener.py
autoreduce_qp/queue_processor/tests/test_variable_utils.py
autoreduce_qp/scripts/__init__.py
autoreduce_qp-21.1.3.dist-info/LICENSE.txt
autoreduce_qp-21.1.3.dist-info/METADATA
autoreduce_qp-21.1.3.dist-info/WHEEL
autoreduce_qp-21.1.3.dist-info/entry_points.txt
autoreduce_qp-21.1.3.dist-info/top_level.txt
autoreduce_qp-21.1.3.dist-info/RECORD
