Metadata-Version: 2.1
Name: autoreduce-qp
Version: 21.1.3
Summary: ISIS Autoreduction queue processor
Home-page: https://github.com/ISISScientificComputing/autoreduce/
Author: ISIS Autoreduction Team
Author-email: UNKNOWN
License: UNKNOWN
Platform: UNKNOWN
Classifier: Programming Language :: Python :: 3 :: Only
Requires-Dist: autoreduce-db (==0.1.4)
Requires-Dist: chardet (==3.0.4)
Requires-Dist: Django (==3.2.2)
Requires-Dist: fire (==0.4.0)
Requires-Dist: plotly (==4.14.3)
Requires-Dist: stomp.py (==6.1.0)
